<?xml version="1.0" ?>
<TLFDetectEngine type="TLFDetectEngine" predictor="TLFAverageNNPredictor">
    <ILFObjectDetector type="TSCObjectDetector">
        <TSCObjectDetector base_width="12" base_height="24" object_type="unknown" detector="ILFObjectDetector">
            <ILFScanner type="TLFScanner" ApertureWidth="12" ApertureHeight="24">
                <TLFParameter type="TLFParameter" m_Value="10.000000" m_MaxValue="100.000000" m_MinValue="1.000000" m_Name="step" m_Descr="step space as a percentage of baseline resolution" />
                <TLFParameter type="TLFParameter" m_Value="1.100000" m_MaxValue="2.000000" m_MinValue="1.100000" m_Name="grow" m_Descr="step on the scale" />
                <TLFParameter type="TLFParameter" m_Value="1.000000" m_MaxValue="4.000000" m_MinValue="1.000000" m_Name="MinSize" m_Descr="min size of scanned object in the BaseWidth" />
                <TLFParameter type="TLFParameter" m_Value="50.000000" m_MaxValue="100.000000" m_MinValue="1.000000" m_Name="MaxSize" m_Descr="max size of scanned object in the BaseWidth" />
            </ILFScanner>
            <CSClassificator threshold="9.559821">
                <CSWeak weigth="1.851592" v0="545294496" v1="16419818" v2="262184" v3="3236954208" v4="276547834" v5="284158970" v6="275923199" v7="83820799" v8="16812714" v9="526346" v10="268437554" v11="262144" v12="287566783" v13="2525870" v14="58" v15="42">
                    <CSFeature sxBase="3" syBase="7" wBase="2" hBase="5" />
                </CSWeak>
                <CSWeak weigth="1.646946" v0="3748159552" v1="2138431608" v2="294932672" v3="1565380801" v4="1534134496" v5="293013730" v6="1364579837" v7="225510654" v8="922751008" v9="285343744" v10="286543936" v11="285295048" v12="301007102" v13="137216" v14="271664375" v15="65538">
                    <CSFeature sxBase="2" syBase="7" wBase="2" hBase="3" />
                </CSWeak>
                <CSWeak weigth="1.420032" v0="2214627488" v1="679389882" v2="2300586096" v3="82024" v4="3606562" v5="7056106" v6="1349517428" v7="74582073" v8="142617192" v9="14878768" v10="2282273762" v11="664336" v12="7449215" v13="5442139" v14="7340067" v15="268501024">
                    <CSFeature sxBase="4" syBase="8" wBase="2" hBase="4" />
                </CSWeak>
                <CSWeak weigth="1.405707" v0="4294459392" v1="2541043720" v2="4271173824" v3="358961280" v4="2138046688" v5="1467416800" v6="3513897169" v7="361840752" v8="2135439432" v9="285229602" v10="412981824" v11="18190336" v12="1356864290" v13="84031748" v14="270298303" v15="134245416">
                    <CSFeature sxBase="2" syBase="5" wBase="2" hBase="3" />
                </CSWeak>
                <CSWeak weigth="1.418931" v0="2155905224" v1="3131816874" v2="3305162752" v3="1111492616" v4="2218" v5="1156558570" v6="4735024" v7="556924986" v8="2281710240" v9="2330146" v10="3355458440" v11="33686018" v12="10530623" v13="494270" v14="3276835" v15="11">
                    <CSFeature sxBase="4" syBase="10" wBase="2" hBase="4" />
                </CSWeak>
                <CSWeak weigth="1.392603" v0="10432" v1="795847280" v2="151029760" v3="151013376" v4="19996912" v5="556477154" v6="391938289" v7="355467488" v8="268437600" v9="24619762" v10="134254608" v11="65552" v12="7416435" v13="50670144" v14="343130291" v15="17039360">
                    <CSFeature sxBase="3" syBase="10" wBase="2" hBase="2" />
                </CSWeak>
                <CSWeak weigth="1.364715" v0="4058042448" v1="565684474" v2="3512746088" v3="1157132780" v4="2440743024" v5="1398254314" v6="3514817015" v7="1482903797" v8="1346375680" v9="29393088" v10="288379936" v11="327176521" v12="275421811" v13="20119561" v14="275775655" v15="131113">
                    <CSFeature sxBase="2" syBase="7" wBase="2" hBase="4" />
                </CSWeak>
                <CSWeak weigth="1.353040" v0="3217605704" v1="391997640" v2="1321492608" v3="1298595912" v4="340263136" v5="1498742792" v6="2471546944" v7="89194513" v8="2145171848" v9="335826944" v10="969774016" v11="85213184" v12="374873056" v13="270875392" v14="452222974" v15="7202">
                    <CSFeature sxBase="2" syBase="3" wBase="2" hBase="3" />
                </CSWeak>
                <CSWeak weigth="1.361498" v0="31457504" v1="2175715808" v2="1644191824" v3="4268980328" v4="1048291424" v5="351714298" v6="3176550903" v7="878908031" v8="1073793904" v9="3238045760" v10="3166440" v11="31490482" v12="3729467" v13="14092600" v14="271712481" v15="394171">
                    <CSFeature sxBase="2" syBase="7" wBase="2" hBase="5" />
                </CSWeak>
                <CSWeak weigth="1.313606" v0="2147518600" v1="3835944" v2="155216584" v3="2148153970" v4="134217856" v5="272629768" v6="2550155834" v7="2147488086" v8="2151721704" v9="24781563" v10="35354" v11="33752816" v12="624699" v13="2818297" v14="269521450" v15="16843264">
                    <CSFeature sxBase="7" syBase="7" wBase="1" hBase="4" />
                </CSWeak>
                <CSWeak weigth="1.351589" v0="33562624" v1="1065216608" v2="2147526720" v3="2653978688" v4="1095794784" v5="6892256" v6="30470577" v7="2432778440" v8="562047616" v9="4285827104" v10="3372222592" v11="1396703360" v12="1074999921" v13="3506866816" v14="494080244" v15="303043264">
                    <CSFeature sxBase="2" syBase="12" wBase="2" hBase="2" />
                </CSWeak>
                <CSWeak weigth="1.355776" v0="4090781760" v1="296034376" v2="288624840" v3="124213450" v4="2532376672" v5="393478368" v6="2503065841" v7="17907948" v8="2134927496" v9="1392623712" v10="420806688" v11="1359003712" v12="3156599" v13="269619586" v14="36782335" v15="16419">
                    <CSFeature sxBase="2" syBase="6" wBase="2" hBase="3" />
                </CSWeak>
                <CSWeak weigth="1.398582" v0="1911605472" v1="34443512" v2="1227905656" v3="139542624" v4="2037858555" v5="456830714" v6="3694543229" v7="346636794" v8="1343228138" v9="34505218" v10="1343654586" v11="2558027" v12="1362737918" v13="281192590" v14="1349683232" v15="6423530">
                    <CSFeature sxBase="3" syBase="5" wBase="2" hBase="5" />
                </CSWeak>
                <CSWeak weigth="1.334631" v0="3235940576" v1="863742186" v2="6302320" v3="21572467" v4="8136752" v5="274705146" v6="7557235" v7="343091945" v8="162572842" v9="6949418" v10="341850279" v11="199609" v12="15411839" v13="18025083" v14="3269155" v15="1245195">
                    <CSFeature sxBase="4" syBase="7" wBase="2" hBase="4" />
                </CSWeak>
            </CSClassificator>
            <CSClassificator threshold="11.361290">
                <CSWeak weigth="1.397979" v0="2151712768" v1="539732650" v2="3707799552" v3="3221334536" v4="268470272" v5="2183342626" v6="3229614080" v7="2701131810" v8="35264" v9="2272162" v10="2550171648" v11="2164295680" v12="9619624" v13="103475360" v14="8388608" v15="67108864">
                    <CSFeature sxBase="4" syBase="13" wBase="2" hBase="3" />
                </CSWeak>
                <CSWeak weigth="1.323091" v0="2143293440" v1="488964616" v2="932986888" v3="458752" v4="1473577152" v5="358940736" v6="1912094800" v7="285474816" v8="2139904844" v9="1361065344" v10="529209346" v11="306540544" v12="324016778" v13="285618688" v14="440338444" v15="2634762">
                    <CSFeature sxBase="2" syBase="4" wBase="2" hBase="3" />
                </CSWeak>
                <CSWeak weigth="1.246925" v0="763387912" v1="1733771264" v2="13369416" v3="1475805955" v4="1162084352" v5="223674368" v6="1073758226" v7="4270355" v8="1292387328" v9="67305728" v10="97255628" v11="332857426" v12="138412042" v13="86179840" v14="1220900189" v15="541336908">
                    <CSFeature sxBase="4" syBase="2" wBase="2" hBase="3" />
                </CSWeak>
                <CSWeak weigth="1.209302" v0="805341312" v1="15853986" v2="2885713952" v3="1383086176" v4="811632810" v5="354921128" v6="23922037" v7="192823547" v8="270532608" v9="1088982400" v10="16785537" v11="291635521" v12="6357098" v13="10520960" v14="2261032" v15="65625">
                    <CSFeature sxBase="2" syBase="10" wBase="2" hBase="4" />
                </CSWeak>
                <CSWeak weigth="1.158814" v0="0" v1="2146452096" v2="1140871296" v3="412127426" v4="234883072" v5="314582016" v6="2231427312" v7="16908480" v8="2147516544" v9="3686268968" v10="128" v11="1395916992" v12="2134902056" v13="3900711050" v14="50385392" v15="4298">
                    <CSFeature sxBase="2" syBase="11" wBase="1" hBase="2" />
                </CSWeak>
                <CSWeak weigth="1.183986" v0="2327873664" v1="614697722" v2="419473472" v3="22036544" v4="171550888" v5="489662714" v6="1077504371" v7="456524410" v8="134217864" v9="62570720" v10="2281711712" v11="54538257" v12="7973499" v13="4327424" v14="6431504" v15="2097208">
                    <CSFeature sxBase="3" syBase="9" wBase="2" hBase="4" />
                </CSWeak>
                <CSWeak weigth="1.126483" v0="79700000" v1="2513772704" v2="12615760" v3="3379274274" v4="421069024" v5="1433665728" v6="277880928" v7="73792" v8="142617256" v9="73596946" v10="4517576" v11="577967088" v12="73607927" v13="1092035170" v14="70354034" v15="33759810">
                    <CSFeature sxBase="4" syBase="7" wBase="2" hBase="2" />
                </CSWeak>
                <CSWeak weigth="1.108020" v0="810592352" v1="463972970" v2="272629760" v3="436455489" v4="343214304" v5="222636266" v6="3594043764" v7="289014763" v8="1405092400" v9="276922369" v10="16793824" v11="856686672" v12="10659962" v13="50538596" v14="355468016" v15="264352">
                    <CSFeature sxBase="3" syBase="8" wBase="2" hBase="3" />
                </CSWeak>
                <CSWeak weigth="1.092869" v0="4241287304" v1="4160391880" v2="2962752712" v3="30443144" v4="4097919200" v5="3570671904" v6="795917" v7="1174478848" v8="3087567008" v9="2000554666" v10="138690998" v11="272629934" v12="340328669" v13="268632227" v14="1347178540" v15="991041447">
                    <CSFeature sxBase="2" syBase="2" wBase="2" hBase="1" />
                </CSWeak>
                <CSWeak weigth="1.140455" v0="1392021600" v1="8421616" v2="1515206760" v3="12637120" v4="1550270696" v5="284526826" v6="733157875" v7="258605691" v8="86258416" v9="270532792" v10="1298159856" v11="29389207" v12="1366268537" v13="275695674" v14="474421280" v15="16973840">
                    <CSFeature sxBase="2" syBase="5" wBase="2" hBase="5" />
                </CSWeak>
                <CSWeak weigth="1.105033" v0="3227551784" v1="625194" v2="35170" v3="0" v4="2189336682" v5="14584938" v6="351764721" v7="13118053" v8="2172659714" v9="36831385" v10="2441088672" v11="2236941" v12="275359787" v13="284133418" v14="7479610" v15="7473969">
                    <CSFeature sxBase="4" syBase="6" wBase="2" hBase="5" />
                </CSWeak>
                <CSWeak weigth="1.153857" v0="3296733248" v1="4285278400" v2="205792320" v3="1837580353" v4="56172752" v5="118336232" v6="630194416" v7="486818016" v8="209723520" v9="1095182848" v10="45696" v11="131328" v12="166996210" v13="117640192" v14="1362199220" v15="459057">
                    <CSFeature sxBase="3" syBase="8" wBase="2" hBase="2" />
                </CSWeak>
                <CSWeak weigth="1.108350" v0="285245440" v1="2043887842" v2="268476608" v3="469469835" v4="8388736" v5="9437312" v6="2768892354" v7="17957586" v8="2768257216" v9="3536982144" v10="20544" v11="273776704" v12="83894336" v13="3490877440" v14="180960" v15="2228410">
                    <CSFeature sxBase="2" syBase="9" wBase="1" hBase="3" />
                </CSWeak>
                <CSWeak weigth="1.138073" v0="1666212064" v1="5013632" v2="1169304064" v3="1523713" v4="308871404" v5="353569000" v6="1114964062" v7="70124259" v8="2005956664" v9="605180080" v10="896811760" v11="288555092" v12="1344512171" v13="282994802" v14="1419055873" v15="38994177">
                    <CSFeature sxBase="3" syBase="5" wBase="2" hBase="4" />
                </CSWeak>
                <CSWeak weigth="1.086651" v0="402653184" v1="2708785296" v2="155222400" v3="339755224" v4="239476896" v5="430252770" v6="334819393" v7="18925796" v8="100672032" v9="3690203688" v10="270528" v11="1135694048" v12="24128240" v13="268766208" v14="100204722" v15="352587976">
                    <CSFeature sxBase="2" syBase="9" wBase="2" hBase="2" />
                </CSWeak>
                <CSWeak weigth="1.114442" v0="2054176960" v1="1213057656" v2="343562472" v3="11010244" v4="1748582624" v5="301793466" v6="1998012522" v7="2097560" v8="1885343832" v9="268435552" v10="1081240280" v11="268569295" v12="272615450" v13="275647656" v14="2125154472" v15="23533674">
                    <CSFeature sxBase="3" syBase="2" wBase="2" hBase="6" />
                </CSWeak>
                <CSWeak weigth="1.137434" v0="2140224" v1="1803266674" v2="2147518568" v3="169134336" v4="17107170" v5="791644386" v6="2562279547" v7="218251480" v8="2149607648" v9="1362331808" v10="2164273664" v11="1095768616" v12="282077794" v13="60066416" v14="14883442" v15="2359400">
                    <CSFeature sxBase="3" syBase="10" wBase="2" hBase="3" />
                </CSWeak>
                <CSWeak weigth="1.059105" v0="16779457" v1="3008659488" v2="2300618752" v3="1695629313" v4="144703616" v5="3499852186" v6="2693922824" v7="4194156577" v8="285284360" v9="470868520" v10="2282989971" v11="1073840866" v12="1804761" v13="335872803" v14="34834823" v15="318768067">
                    <CSFeature sxBase="4" syBase="19" wBase="2" hBase="1" />
                </CSWeak>
                <CSWeak weigth="1.107570" v0="674398336" v1="11010240" v2="3165157408" v3="1080054098" v4="2034172152" v5="164923627" v6="3094040656" v7="112722299" v8="3632293888" v9="24792" v10="1279280728" v11="13911025" v12="32544890" v13="6981904" v14="2706833762" v15="4522008">
                    <CSFeature sxBase="2" syBase="4" wBase="2" hBase="6" />
                </CSWeak>
                <CSWeak weigth="1.142866" v0="2281736200" v1="575080488" v2="2348853832" v3="193196571" v4="134225920" v5="33554432" v6="134275584" v7="290460433" v8="4205160" v9="307702322" v10="2151735004" v11="51587674" v12="5253243" v13="270207098" v14="1155106" v15="1188362">
                    <CSFeature sxBase="7" syBase="7" wBase="1" hBase="3" />
                </CSWeak>
            </CSClassificator>
            <CSClassificator threshold="12.549807">
                <CSWeak weigth="1.163908" v0="33562624" v1="1755328640" v2="318788064" v3="294138312" v4="0" v5="33554432" v6="856215792" v7="50467008" v8="2315809280" v9="4085403776" v10="33583168" v11="302010560" v12="512" v13="8736" v14="286642256" v15="0">
                    <CSFeature sxBase="2" syBase="8" wBase="1" hBase="2" />
                </CSWeak>
                <CSWeak weigth="1.054569" v0="3162144" v1="268468224" v2="100795104" v3="6304264" v4="2130346168" v5="464620200" v6="1488846970" v7="337772768" v8="19982978" v9="7899822" v10="270552762" v11="7580219" v12="12553006" v13="301377710" v14="3350816" v15="6758632">
                    <CSFeature sxBase="4" syBase="5" wBase="2" hBase="5" />
                </CSWeak>
                <CSWeak weigth="0.938821" v0="1060634624" v1="117784584" v2="885018688" v3="392515720" v4="4145807520" v5="1428357344" v6="1882243296" v7="310722809" v8="2064136768" v9="2466263042" v10="529625664" v11="318836961" v12="424686504" v13="268843776" v14="140264526" v15="201616650">
                    <CSFeature sxBase="2" syBase="5" wBase="2" hBase="3" />
                </CSWeak>
                <CSWeak weigth="0.924443" v0="12591168" v1="3208424104" v2="8388608" v3="998287360" v4="2163212528" v5="1081551600" v6="274989168" v7="35651680" v8="8420" v9="291185152" v10="2285939712" v11="33556481" v12="19933940" v13="33622242" v14="272072952" v15="117645922">
                    <CSFeature sxBase="4" syBase="11" wBase="2" hBase="2" />
                </CSWeak>
                <CSWeak weigth="0.928837" v0="893403200" v1="1985287168" v2="92553792" v3="125244144" v4="352845824" v5="354877440" v6="345257992" v7="71313075" v8="2902736904" v9="18284546" v10="25989640" v11="89595986" v12="137456640" v13="354619432" v14="1089007964" v15="537031507">
                    <CSFeature sxBase="4" syBase="3" wBase="2" hBase="3" />
                </CSWeak>
                <CSWeak weigth="0.932900" v0="1409288192" v1="2067769888" v2="1109393408" v3="1601358018" v4="1146101760" v5="209168554" v6="18500" v7="225726578" v8="2476769920" v9="1408411809" v10="58777600" v11="837947521" v12="293808240" v13="310673640" v14="31466022" v15="25166036">
                    <CSFeature sxBase="2" syBase="11" wBase="2" hBase="3" />
                </CSWeak>
                <CSWeak weigth="0.895476" v0="1378959360" v1="1905049632" v2="1756413968" v3="1427169760" v4="367050930" v5="833028330" v6="4038117501" v7="342098171" v8="271610208" v9="268492928" v10="1414850704" v11="22360104" v12="409749934" v13="6688908" v14="410730633" v15="268587569">
                    <CSFeature sxBase="2" syBase="5" wBase="2" hBase="4" />
                </CSWeak>
                <CSWeak weigth="0.902539" v0="67141696" v1="2577664672" v2="4096" v3="2451888328" v4="219685056" v5="159722224" v6="328235232" v7="419447010" v8="270565536" v9="3949736490" v10="17039360" v11="430998144" v12="7381744" v13="352651776" v14="276037872" v15="352338249">
                    <CSFeature sxBase="2" syBase="10" wBase="2" hBase="2" />
                </CSWeak>
                <CSWeak weigth="0.903866" v0="12615744" v1="2216788000" v2="280264868" v3="122028592" v4="3627624636" v5="1606254818" v6="2759590271" v7="111825017" v8="1614807056" v9="277479584" v10="269511312" v11="51380272" v12="276015807" v13="285089985" v14="276234261" v15="2105402">
                    <CSFeature sxBase="3" syBase="7" wBase="2" hBase="4" />
                </CSWeak>
                <CSWeak weigth="0.871227" v0="874520576" v1="1141319784" v2="3229614080" v3="957154049" v4="1421082632" v5="1427319530" v6="1343553580" v7="67306035" v8="2315258016" v9="35076106" v10="649940" v11="58157299" v12="7351039" v13="69281794" v14="280363764" v15="52822588">
                    <CSFeature sxBase="4" syBase="7" wBase="2" hBase="3" />
                </CSWeak>
                <CSWeak weigth="0.903757" v0="119554184" v1="143067648" v2="3127951384" v3="1362233442" v4="1190985968" v5="359071936" v6="338919524" v7="4587771" v8="1931276360" v9="67293256" v10="1063645586" v11="2231550112" v12="14685048" v13="268570652" v14="1060900365" v15="205858099">
                    <CSFeature sxBase="2" syBase="3" wBase="2" hBase="4" />
                </CSWeak>
                <CSWeak weigth="0.889737" v0="3290472448" v1="4181239840" v2="3590324224" v3="2351988944" v4="0" v5="481208938" v6="33554505" v7="1236533363" v8="2147520896" v9="4059211904" v10="2424340480" v11="2154893696" v12="339935416" v13="2218846376" v14="396923026" v15="8458273">
                    <CSFeature sxBase="2" syBase="13" wBase="2" hBase="3" />
                </CSWeak>
                <CSWeak weigth="0.902740" v0="2147485696" v1="673753640" v2="2151705096" v3="161590098" v4="134217728" v5="65546" v6="16777728" v7="50332481" v8="2151737906" v9="309535288" v10="2152764120" v11="51577521" v12="5278306" v13="7801459" v14="1222699" v15="42">
                    <CSFeature sxBase="7" syBase="8" wBase="1" hBase="3" />
                </CSWeak>
                <CSWeak weigth="0.908657" v0="1660997632" v1="76578874" v2="989911144" v3="1808980155" v4="33587200" v5="67108864" v6="2150658515" v7="357783771" v8="3540054208" v9="3237011584" v10="1124116736" v11="318767128" v12="1091059778" v13="276971584" v14="96551440" v15="12718410">
                    <CSFeature sxBase="2" syBase="5" wBase="1" hBase="4" />
                </CSWeak>
                <CSWeak weigth="0.895894" v0="2290098176" v1="2243698784" v2="12591296" v3="3378229972" v4="210305024" v5="3246718976" v6="358105168" v7="218395408" v8="10440" v9="1125584897" v10="147372240" v11="856761938" v12="10559712" v13="1159792739" v14="11739860" v15="54732879">
                    <CSFeature sxBase="4" syBase="6" wBase="2" hBase="2" />
                </CSWeak>
                <CSWeak weigth="0.852390" v0="1886404616" v1="1149356032" v2="3933790304" v3="34915040" v4="3522969632" v5="293142752" v6="942669858" v7="270615035" v8="1344303296" v9="318886320" v10="1920049424" v11="319129808" v12="2159677864" v13="417857" v14="439697929" v15="4531270">
                    <CSFeature sxBase="2" syBase="4" wBase="2" hBase="4" />
                </CSWeak>
                <CSWeak weigth="0.906366" v0="34816" v1="528198312" v2="2306902080" v3="436742792" v4="8288" v5="2309302864" v6="2491416720" v7="16777296" v8="41064" v9="23075328" v10="4241408" v11="33587202" v12="24324720" v13="86212834" v14="91660978" v15="16777505">
                    <CSFeature sxBase="4" syBase="12" wBase="2" hBase="2" />
                </CSWeak>
                <CSWeak weigth="0.899308" v0="177209344" v1="1426866176" v2="1145323520" v3="51707969" v4="1055916136" v5="1563830944" v6="2492485748" v7="521081573" v8="520101984" v9="285278273" v10="906604608" v11="22351988" v12="91859188" v13="289611892" v14="1083741409" v15="268566816">
                    <CSFeature sxBase="3" syBase="6" wBase="2" hBase="3" />
                </CSWeak>
                <CSWeak weigth="0.885097" v0="7340032" v1="540381248" v2="7346922" v3="17903720" v4="3572891816" v5="300746890" v6="427624544" v7="339353697" v8="1090552336" v9="1049232" v10="1366294750" v11="1074993907" v12="284362787" v13="16187582" v14="298910464" v15="5255561">
                    <CSFeature sxBase="4" syBase="3" wBase="2" hBase="5" />
                </CSWeak>
                <CSWeak weigth="0.888640" v0="3624411200" v1="3787729064" v2="704655488" v3="3460685888" v4="2232680608" v5="1084490472" v6="591451121" v7="352342224" v8="2181333024" v9="4193268361" v10="671355408" v11="545272000" v12="32907459" v13="210052" v14="422777976" v15="84169120">
                    <CSFeature sxBase="2" syBase="8" wBase="2" hBase="2" />
                </CSWeak>
                <CSWeak weigth="0.886356" v0="285755488" v1="1007648840" v2="1631920224" v3="285278209" v4="1458569376" v5="455739638" v6="3022457118" v7="103858377" v8="455084128" v9="70582408" v10="285307520" v11="810619395" v12="7514362" v13="68364380" v14="1152723084" v15="88277164">
                    <CSFeature sxBase="3" syBase="7" wBase="2" hBase="3" />
                </CSWeak>
                <CSWeak weigth="0.888200" v0="2387124234" v1="3838575104" v2="3938458828" v3="339779744" v4="3380609032" v5="2361393216" v6="73158864" v7="1291882496" v8="2294844040" v9="2524979458" v10="69487052" v11="907018916" v12="67240008" v13="1359032418" v14="18275689" v15="859390955">
                    <CSFeature sxBase="2" syBase="4" wBase="2" hBase="1" />
                </CSWeak>
                <CSWeak weigth="0.922052" v0="1382039584" v1="321437824" v2="2282811400" v3="379641968" v4="3572484128" v5="2579335266" v6="61739089" v7="405828348" v8="3313787472" v9="270553277" v10="342906960" v11="297865381" v12="283873329" v13="116960" v14="343085120" v15="4391307">
                    <CSFeature sxBase="2" syBase="5" wBase="2" hBase="5" />
                </CSWeak>
                <CSWeak weigth="0.868674" v0="746078456" v1="823574656" v2="2142511210" v3="1621676738" v4="2242969656" v5="15204594" v6="699499320" v7="346558935" v8="1167642960" v9="2154608" v10="2121298640" v11="24142584" v12="1348759737" v13="2506930" v14="406205077" v15="273821956">
                    <CSFeature sxBase="2" syBase="3" wBase="2" hBase="5" />
                </CSWeak>
                <CSWeak weigth="0.890556" v0="570949696" v1="3934441672" v2="58757458" v3="2487259328" v4="2756067904" v5="2183576064" v6="285650481" v7="1074004033" v8="2382372872" v9="3349736448" v10="83887312" v11="17106176" v12="2114302980" v13="4279219008" v14="123214224" v15="459084114">
                    <CSFeature sxBase="2" syBase="12" wBase="1" hBase="1" />
                </CSWeak>
                <CSWeak weigth="0.914574" v0="3003154464" v1="940022016" v2="2589983264" v3="2063749744" v4="350324896" v5="1419225706" v6="2346010723" v7="1578518911" v8="1635795072" v9="1098940888" v10="16448" v11="2240723" v12="4334139" v13="107414044" v14="282198031" v15="19136825">
                    <CSFeature sxBase="2" syBase="9" wBase="2" hBase="4" />
                </CSWeak>
                <CSWeak weigth="0.872296" v0="32896" v1="2669718080" v2="3229646848" v3="3935863296" v4="128" v5="1572874" v6="3254788112" v7="3843031168" v8="34948" v9="3534752" v10="2827009024" v11="3020016128" v12="100270768" v13="94809009" v14="401904120" v15="83886592">
                    <CSFeature sxBase="3" syBase="16" wBase="2" hBase="2" />
                </CSWeak>
                <CSWeak weigth="0.879097" v0="1378942976" v1="104694346" v2="141557872" v3="118948546" v4="2499543224" v5="1361848474" v6="806355185" v7="74514769" v8="321956066" v9="38928992" v10="269501390" v11="342434171" v12="137374390" v13="293603892" v14="2148385" v15="5575546">
                    <CSFeature sxBase="4" syBase="5" wBase="2" hBase="4" />
                </CSWeak>
            </CSClassificator>
            <CSClassificator threshold="13.190605">
                <CSWeak weigth="1.073723" v0="69238784" v1="1089513632" v2="49248" v3="745558113" v4="70469682" v5="372189222" v6="3223411061" v7="1333023863" v8="2147487808" v9="1088431128" v10="2416984274" v11="40977232" v12="206895" v13="10305" v14="1075855407" v15="58">
                    <CSFeature sxBase="2" syBase="8" wBase="2" hBase="4" />
                </CSWeak>
                <CSWeak weigth="0.869822" v0="10304" v1="528444128" v2="2147483648" v3="2198341632" v4="2151686352" v5="2879727842" v6="2224079216" v7="2097248" v8="34080816" v9="628304416" v10="559104" v11="55580673" v12="13707378" v13="151267392" v14="288465138" v15="67113026">
                    <CSFeature sxBase="3" syBase="11" wBase="2" hBase="2" />
                </CSWeak>
                <CSWeak weigth="0.837483" v0="2151712768" v1="1278120" v2="2436893192" v3="2684396096" v4="134217736" v5="276889608" v6="1207967744" v7="1074790400" v8="2155915938" v9="16394875" v10="2568" v11="8434" v12="5343275" v13="3866683" v14="40" v15="0">
                    <CSFeature sxBase="7" syBase="9" wBase="1" hBase="4" />
                </CSWeak>
                <CSWeak weigth="0.801032" v0="455100520" v1="20975760" v2="89180256" v3="2803893088" v4="3460243562" v5="277758200" v6="1601654905" v7="273635450" v8="1863350384" v9="6336833" v10="3553720934" v11="291648360" v12="1352913017" v13="21303480" v14="2571119624" v15="33771656">
                    <CSFeature sxBase="2" syBase="4" wBase="2" hBase="5" />
                </CSWeak>
                <CSWeak weigth="0.790949" v0="14417984" v1="54788096" v2="12599488" v3="3234660416" v4="33554440" v5="3448111104" v6="4735056" v7="1816150016" v8="2290884616" v9="2887320577" v10="12587208" v11="224" v12="293603337" v13="285868100" v14="1413772660" v15="1531474257">
                    <CSFeature sxBase="4" syBase="2" wBase="2" hBase="2" />
                </CSWeak>
                <CSWeak weigth="0.766859" v0="536870912" v1="2075918528" v2="67109088" v3="2497218696" v4="310380288" v5="1140865024" v6="1089686" v7="68419778" v8="671138816" v9="4214301993" v10="1024" v11="1109426593" v12="3294250496" v13="1840667883" v14="1494270448" v15="1079641430">
                    <CSFeature sxBase="2" syBase="12" wBase="1" hBase="2" />
                </CSWeak>
                <CSWeak weigth="0.786952" v0="2437974208" v1="2689108096" v2="272671248" v3="605307488" v4="3513886772" v5="489294415" v6="3625110873" v7="3693173" v8="1343258752" v9="32920" v10="353421449" v11="285610048" v12="271779903" v13="340295755" v14="286493448" v15="34865853">
                    <CSFeature sxBase="3" syBase="6" wBase="2" hBase="4" />
                </CSWeak>
                <CSWeak weigth="0.790202" v0="96" v1="2496993504" v2="151267328" v3="3378559009" v4="106688" v5="1226899552" v6="29425712" v7="268567186" v8="142909672" v9="92536914" v10="552480" v11="57737938" v12="24161009" v13="318975040" v14="22317751" v15="352519937">
                    <CSFeature sxBase="4" syBase="8" wBase="2" hBase="2" />
                </CSWeak>
                <CSWeak weigth="0.784273" v0="8200" v1="2053242912" v2="67117088" v3="997857513" v4="8416256" v5="136380544" v6="273760884" v7="1121780458" v8="2424340864" v9="1886409121" v10="16777416" v11="324272466" v12="1946866570" v13="2119832021" v14="20877976" v15="13500506">
                    <CSFeature sxBase="2" syBase="12" wBase="1" hBase="3" />
                </CSWeak>
                <CSWeak weigth="0.758328" v0="745595456" v1="3230728210" v2="274762288" v3="38209834" v4="1433403616" v5="1433403400" v6="280240152" v7="73862983" v8="385907432" v9="73402368" v10="72353834" v11="392652988" v12="292719358" v13="123732041" v14="576278797" v15="5584725">
                    <CSFeature sxBase="4" syBase="3" wBase="2" hBase="4" />
                </CSWeak>
                <CSWeak weigth="0.794094" v0="2147516928" v1="1248561826" v2="25168384" v3="3363045888" v4="18909280" v5="740968480" v6="2149892187" v7="125173950" v8="25168000" v9="62951554" v10="2365589920" v11="54596162" v12="2162494071" v13="8816660" v14="15810611" v15="18940203">
                    <CSFeature sxBase="3" syBase="10" wBase="2" hBase="4" />
                </CSWeak>
                <CSWeak weigth="0.799327" v0="3138928656" v1="3372687392" v2="206307328" v3="50659921" v4="3220504640" v5="460587040" v6="2046328944" v7="1124078307" v8="738197666" v9="290787408" v10="117707264" v11="910500371" v12="89137384" v13="19333776" v14="144461036" v15="40108292">
                    <CSFeature sxBase="3" syBase="5" wBase="2" hBase="3" />
                </CSWeak>
                <CSWeak weigth="0.773915" v0="34944" v1="1866369114" v2="2160120000" v3="219195400" v4="1048800" v5="153168456" v6="2151727312" v7="1065330" v8="52430848" v9="2054856226" v10="134219776" v11="124830464" v12="90251408" v13="338764512" v14="462696880" v15="1279528960">
                    <CSFeature sxBase="2" syBase="13" wBase="2" hBase="2" />
                </CSWeak>
                <CSWeak weigth="0.780892" v0="4226809952" v1="1016856768" v2="2188959840" v3="943751920" v4="3295690834" v5="3513460776" v6="2217920997" v7="1584662909" v8="1342230560" v9="268456000" v10="1934708944" v11="274004435" v12="2417047609" v13="289624229" v14="268697893" v15="182">
                    <CSFeature sxBase="2" syBase="6" wBase="2" hBase="4" />
                </CSWeak>
                <CSWeak weigth="0.747428" v0="2285928672" v1="579903498" v2="43584" v3="57974784" v4="1383467616" v5="497887341" v6="287369271" v7="67387646" v8="2148567264" v9="8618070" v10="285224624" v11="33583674" v12="7479355" v13="22218821" v14="275939878" v15="1048845">
                    <CSFeature sxBase="3" syBase="8" wBase="2" hBase="4" />
                </CSWeak>
                <CSWeak weigth="0.742692" v0="201336864" v1="2506819808" v2="134225920" v3="3122022448" v4="193003728" v5="136587786" v6="499451313" v7="159645920" v8="285214848" v9="1684078608" v10="43072" v11="72257" v12="4369141" v13="1124401984" v14="292585970" v15="318833778">
                    <CSFeature sxBase="3" syBase="9" wBase="2" hBase="2" />
                </CSWeak>
                <CSWeak weigth="0.744098" v0="2160887808" v1="268445728" v2="2424342528" v3="1308690432" v4="12583048" v5="1350566168" v6="1883242496" v7="1439826177" v8="642" v9="2149839538" v10="2172700672" v11="1795181056" v12="9308360" v13="581417632" v14="9732746" v15="393992">
                    <CSFeature sxBase="4" syBase="16" wBase="2" hBase="2" />
                </CSWeak>
                <CSWeak weigth="0.774295" v0="25167872" v1="528230440" v2="20480" v3="258592834" v4="2499807344" v5="422423054" v6="2690935141" v7="225099948" v8="1367384192" v9="4042787042" v10="1360003136" v11="318984387" v12="275751667" v13="38938696" v14="296751394" v15="285212713">
                    <CSFeature sxBase="2" syBase="9" wBase="2" hBase="3" />
                </CSWeak>
                <CSWeak weigth="0.782902" v0="989914112" v1="825753640" v2="861405184" v3="486867024" v4="500170752" v5="356843520" v6="1412169792" v7="218104368" v8="2131264128" v9="117444744" v10="478785796" v11="20971520" v12="104872706" v13="268448544" v14="1280183501" v15="975645194">
                    <CSFeature sxBase="2" syBase="2" wBase="2" hBase="3" />
                </CSWeak>
                <CSWeak weigth="0.797358" v0="33587200" v1="792600800" v2="2164295808" v3="1130392217" v4="0" v5="3358861408" v6="2151688320" v7="2169766232" v8="41600" v9="2000133040" v10="2164320384" v11="997222528" v12="1095107232" v13="371990672" v14="327164048" v15="374341634">
                    <CSFeature sxBase="2" syBase="14" wBase="2" hBase="2" />
                </CSWeak>
                <CSWeak weigth="0.779809" v0="3228598464" v1="593070240" v2="2214756936" v3="322961410" v4="2054686778" v5="463014506" v6="154304688" v7="72098400" v8="2307915810" v9="275808391" v10="274744360" v11="6457882" v12="5377971" v13="284133562" v14="23142624" v15="7602778">
                    <CSFeature sxBase="4" syBase="5" wBase="2" hBase="5" />
                </CSWeak>
                <CSWeak weigth="0.763858" v0="1618018400" v1="3758800992" v2="2427469880" v3="1088578464" v4="3515924514" v5="867041466" v6="3652275509" v7="67125448" v8="3878711648" v9="1347481728" v10="303100048" v11="6648160" v12="1383092326" v13="2232460" v14="1563344939" v15="272781937">
                    <CSFeature sxBase="2" syBase="5" wBase="2" hBase="4" />
                </CSWeak>
                <CSWeak weigth="0.770287" v0="104874688" v1="3381674368" v2="76203160" v3="3422596034" v4="92947168" v5="1712142920" v6="660468" v7="319031298" v8="1174425792" v9="2934710945" v10="67643888" v11="1162871120" v12="479199904" v13="3110376985" v14="1326191577" v15="1296061523">
                    <CSFeature sxBase="2" syBase="13" wBase="1" hBase="1" />
                </CSWeak>
                <CSWeak weigth="0.775555" v0="405274688" v1="537428192" v2="208330752" v3="14729554" v4="754254056" v5="2225668322" v6="469715633" v7="1115689070" v8="738214992" v9="2148544544" v10="1543568032" v11="13648194" v12="312051737" v13="7225545" v14="271659008" v15="22091227">
                    <CSFeature sxBase="2" syBase="3" wBase="2" hBase="6" />
                </CSWeak>
                <CSWeak weigth="0.778609" v0="3355475968" v1="2148116712" v2="2902468896" v3="37748800" v4="338080" v5="1152363234" v6="268976177" v7="70254705" v8="2147526758" v9="10553360" v10="8415818" v11="50344521" v12="7482033" v13="41814083" v14="3147797" v15="19988760">
                    <CSFeature sxBase="4" syBase="9" wBase="2" hBase="4" />
                </CSWeak>
                <CSWeak weigth="0.779032" v0="2573252736" v1="1476659234" v2="671088704" v3="225761416" v4="3589275880" v5="88803996" v6="1921007760" v7="356018431" v8="2424349362" v9="1372594304" v10="289488960" v11="1404813339" v12="15796739" v13="335544384" v14="70254708" v15="19152946">
                    <CSFeature sxBase="2" syBase="8" wBase="2" hBase="3" />
                </CSWeak>
                <CSWeak weigth="0.736753" v0="8398848" v1="716579386" v2="2281742872" v3="718287872" v4="134217728" v5="301140475" v6="149422080" v7="2148573248" v8="2147494001" v9="56623666" v10="2181096096" v11="33567240" v12="4204667" v13="28314305" v14="67642" v15="131936">
                    <CSFeature sxBase="7" syBase="12" wBase="1" hBase="2" />
                </CSWeak>
                <CSWeak weigth="0.757211" v0="1086357536" v1="1927162496" v2="2147518464" v3="2466581120" v4="84148320" v5="96537330" v6="442511504" v7="85991488" v8="7296" v9="1378881603" v10="138719360" v11="51448338" v12="22022773" v13="117770820" v14="7573206" v15="83954434">
                    <CSFeature sxBase="4" syBase="9" wBase="2" hBase="2" />
                </CSWeak>
                <CSWeak weigth="0.757351" v0="4227296" v1="3767839304" v2="9734276" v3="343280128" v4="1364273236" v5="1538918986" v6="3830794619" v7="119554267" v8="1611723392" v9="270008914" v10="269492248" v11="50334306" v12="276867641" v13="5245643" v14="285376516" v15="73769">
                    <CSFeature sxBase="3" syBase="7" wBase="2" hBase="4" />
                </CSWeak>
                <CSWeak weigth="0.789779" v0="1958752968" v1="3454698672" v2="79718528" v3="1522816680" v4="713033920" v5="4072964736" v6="2419914607" v7="286525568" v8="2181563096" v9="2316698016" v10="67143136" v11="272900130" v12="96993315" v13="723648906" v14="455547724" v15="55186249">
                    <CSFeature sxBase="4" syBase="2" wBase="2" hBase="1" />
                </CSWeak>
                <CSWeak weigth="0.753774" v0="1073762312" v1="1382072416" v2="3242197408" v3="1528301802" v4="1254393344" v5="85459073" v6="10094626" v7="1091961167" v8="310420416" v9="1417396609" v10="293765264" v11="324010368" v12="2009666272" v13="1726218456" v14="571241538" v15="1076510942">
                    <CSFeature sxBase="2" syBase="13" wBase="1" hBase="3" />
                </CSWeak>
                <CSWeak weigth="0.782653" v0="2181046336" v1="384207600" v2="79728880" v3="2308628744" v4="3254796488" v5="3904897136" v6="281183136" v7="2147500048" v8="10782858" v9="3226534227" v10="68158608" v11="1677734483" v12="2403867963" v13="134080771" v14="1158948881" v15="1141182801">
                    <CSFeature sxBase="6" syBase="7" wBase="1" hBase="1" />
                </CSWeak>
                <CSWeak weigth="0.789632" v0="2584772832" v1="69239442" v2="2403056" v3="8208896" v4="548290592" v5="1303316584" v6="2645723249" v7="338690801" v8="1097908384" v9="287592632" v10="1349828826" v11="54919375" v12="1083355169" v13="12595401" v14="284304233" v15="5446331">
                    <CSFeature sxBase="3" syBase="4" wBase="2" hBase="5" />
                </CSWeak>
                <CSWeak weigth="0.774623" v0="91246608" v1="2449637520" v2="60872810" v3="1686151842" v4="1965392104" v5="1371275506" v6="212158963" v7="92799441" v8="1905283360" v9="2126032" v10="124829792" v11="20992008" v12="1351053427" v13="290476280" v14="319492713" v15="5714070">
                    <CSFeature sxBase="2" syBase="3" wBase="2" hBase="5" />
                </CSWeak>
            </CSClassificator>
            <CSClassificator threshold="13.983355">
                <CSWeak weigth="0.877231" v0="33570816" v1="1355940032" v2="8400" v3="1926296307" v4="0" v5="128" v6="335556818" v7="269627984" v8="1073743872" v9="3495755784" v10="33554432" v11="34605779" v12="524288" v13="1427308584" v14="285241684" v15="4292">
                    <CSFeature sxBase="7" syBase="4" wBase="1" hBase="2" />
                </CSWeak>
                <CSWeak weigth="0.745629" v0="32896" v1="186384512" v2="3221258240" v3="2639282306" v4="8421504" v5="2284882080" v6="2096" v7="3221291008" v8="857774208" v9="1114826912" v10="1208008704" v11="2521860098" v12="19365920" v13="217234144" v14="353390776" v15="1380192288">
                    <CSFeature sxBase="2" syBase="15" wBase="2" hBase="2" />
                </CSWeak>
                <CSWeak weigth="0.732783" v0="2332035584" v1="511705792" v2="587224032" v3="2584269000" v4="16777728" v5="33554432" v6="423948528" v7="453050496" v8="2281714312" v9="192946256" v10="302051664" v11="301994308" v12="2600" v13="369640192" v14="419483752" v15="67108872">
                    <CSFeature sxBase="2" syBase="7" wBase="1" hBase="2" />
                </CSWeak>
                <CSWeak weigth="0.688509" v0="292602048" v1="2673887424" v2="6332930" v3="3552947" v4="1979187280" v5="287309824" v6="3560047154" v7="69282401" v8="337684514" v9="578027626" v10="323344037" v11="23558559" v12="158565027" v13="69339136" v14="917509" v15="7550149">
                    <CSFeature sxBase="4" syBase="4" wBase="2" hBase="4" />
                </CSWeak>
                <CSWeak weigth="0.670414" v0="67109888" v1="1874461256" v2="536873632" v3="2471657600" v4="2231388288" v5="4061136896" v6="3289616000" v7="1079181760" v8="1761616904" v9="4139263240" v10="67325952" v11="1379271784" v12="1996528914" v13="3560059380" v14="1260287448" v15="1156584672">
                    <CSFeature sxBase="2" syBase="13" wBase="1" hBase="2" />
                </CSWeak>
                <CSWeak weigth="0.661015" v0="315645952" v1="3076792328" v2="3091517504" v3="341919882" v4="1464926336" v5="257949888" v6="3494953041" v7="23347428" v8="994056328" v9="319815712" v10="486823968" v11="319942816" v12="356592373" v13="335552914" v14="46009645" v15="100663363">
                    <CSFeature sxBase="2" syBase="6" wBase="2" hBase="3" />
                </CSWeak>
                <CSWeak weigth="0.667306" v0="56655872" v1="3141347362" v2="335544384" v3="793788992" v4="4718656" v5="74255086" v6="2425405505" v7="527974516" v8="3248531458" v9="3244315274" v10="2101504" v11="1126379914" v12="2203884" v13="1204650188" v14="82837571" v15="65547">
                    <CSFeature sxBase="2" syBase="10" wBase="2" hBase="3" />
                </CSWeak>
                <CSWeak weigth="0.699959" v0="4032876608" v1="2417975296" v2="102271216" v3="891748834" v4="1366294528" v5="1362231296" v6="2361896" v7="1081287171" v8="487090816" v9="2491456" v10="33851432" v11="58138636" v12="19940514" v13="270563448" v14="944574533" v15="1178556287">
                    <CSFeature sxBase="4" syBase="2" wBase="2" hBase="4" />
                </CSWeak>
                <CSWeak weigth="0.656506" v0="682770656" v1="2156396736" v2="2796044384" v3="2026430834" v4="1227915424" v5="2490608" v6="976228890" v7="279712168" v8="2550184000" v9="28744" v10="1287668424" v11="17056488" v12="17667080" v13="22774161" v14="2718122149" v15="327948">
                    <CSFeature sxBase="2" syBase="4" wBase="2" hBase="6" />
                </CSWeak>
                <CSWeak weigth="0.641047" v0="167805440" v1="2416181824" v2="10312" v3="196666" v4="268435648" v5="0" v6="1207965898" v7="2294387" v8="2147516936" v9="7735528" v10="268468392" v11="21635322" v12="269123752" v13="283836554" v14="135804716" v15="35323946">
                    <CSFeature sxBase="7" syBase="3" wBase="1" hBase="5" />
                </CSWeak>
                <CSWeak weigth="0.647822" v0="372041888" v1="2171994136" v2="2424889448" v3="1406673024" v4="2013399137" v5="293896288" v6="575938" v7="117445776" v8="702064745" v9="285917189" v10="808240220" v11="16976064" v12="495125209" v13="16777739" v14="223621071" v15="1931675471">
                    <CSFeature sxBase="3" syBase="2" wBase="2" hBase="1" />
                </CSWeak>
                <CSWeak weigth="0.677604" v0="3203432608" v1="979664898" v2="3245867008" v3="1766883408" v4="300662962" v5="2147879018" v6="1109426209" v7="1499605062" v8="4032844000" v9="285225112" v10="587288592" v11="285501843" v12="2443391017" v13="18897077" v14="272974305" v15="268697601">
                    <CSFeature sxBase="2" syBase="6" wBase="2" hBase="4" />
                </CSWeak>
                <CSWeak weigth="0.636692" v0="805321416" v1="1616953352" v2="855699840" v3="482410656" v4="4194304" v5="117440512" v6="1660997842" v7="134234186" v8="838883528" v9="1577087392" v10="268484608" v11="16777296" v12="16800288" v13="69840" v14="303623803" v15="1146159145">
                    <CSFeature sxBase="2" syBase="5" wBase="1" hBase="3" />
                </CSWeak>
                <CSWeak weigth="0.654546" v0="448823424" v1="1663576706" v2="427819616" v3="23118400" v4="40706080" v5="331817008" v6="1278749045" v7="49283127" v8="142608904" v9="25870848" v10="2298489312" v11="55580753" v12="15870527" v13="12782200" v14="7482151" v15="3342337">
                    <CSFeature sxBase="3" syBase="9" wBase="2" hBase="4" />
                </CSWeak>
                <CSWeak weigth="0.678834" v0="2043150336" v1="318865504" v2="2903506992" v3="401937008" v4="1369514128" v5="393281634" v6="3297943584" v7="75375345" v8="1962971264" v9="86003728" v10="1501827298" v11="285679674" v12="275884584" v13="12322888" v14="235680909" v15="282464545">
                    <CSFeature sxBase="3" syBase="4" wBase="2" hBase="4" />
                </CSWeak>
                <CSWeak weigth="0.641227" v0="0" v1="2407587968" v2="167776976" v3="54587520" v4="2751466176" v5="3358327496" v6="118018288" v7="151257409" v8="2852184192" v9="4222890113" v10="134237696" v11="286261520" v12="2383479492" v13="3007315976" v14="184554320" v15="117441488">
                    <CSFeature sxBase="2" syBase="11" wBase="1" hBase="1" />
                </CSWeak>
                <CSWeak weigth="0.653149" v0="1123057720" v1="75876564" v2="3347073130" v3="761557824" v4="1530691642" v5="1088162136" v6="3174388592" v7="906064636" v8="27152" v9="2153387240" v10="1265654388" v11="4595715" v12="271620873" v13="37718032" v14="1078198713" v15="285606091">
                    <CSFeature sxBase="2" syBase="6" wBase="2" hBase="5" />
                </CSWeak>
                <CSWeak weigth="0.655743" v0="1082130657" v1="2181070848" v2="3045376008" v3="3137700144" v4="2475032609" v5="2466386176" v6="3229811163" v7="4267970593" v8="1351393792" v9="84533379" v10="3016014168" v11="1997635751" v12="63701825" v13="4171272608" v14="252192534" v15="21168356">
                    <CSFeature sxBase="2" syBase="19" wBase="2" hBase="1" />
                </CSWeak>
                <CSWeak weigth="0.669176" v0="2928148480" v1="2514616320" v2="155464256" v3="1006911680" v4="2383741056" v5="31719504" v6="805396960" v7="50385089" v8="2726562304" v9="159711753" v10="788804488" v11="50369297" v12="33620608" v13="1157960738" v14="508757170" v15="285294784">
                    <CSFeature sxBase="2" syBase="7" wBase="2" hBase="2" />
                </CSWeak>
                <CSWeak weigth="0.664907" v0="2160066624" v1="336201920" v2="33376" v3="50659360" v4="22266604" v5="142551175" v6="152783409" v7="2113650" v8="2148565216" v9="1247334" v10="285216432" v11="33575514" v12="5737002" v13="264205" v14="285378669" v15="2228284">
                    <CSFeature sxBase="3" syBase="8" wBase="2" hBase="4" />
                </CSWeak>
                <CSWeak weigth="0.658197" v0="1191198880" v1="4222257824" v2="2487899824" v3="3473062272" v4="1108352744" v5="1174938176" v6="1145175810" v7="541335600" v8="67162112" v9="3741942440" v10="117714256" v11="1078985885" v12="140854068" v13="1623802450" v14="1263141124" v15="64231257">
                    <CSFeature sxBase="2" syBase="16" wBase="1" hBase="1" />
                </CSWeak>
                <CSWeak weigth="0.658584" v0="1654706384" v1="1752268890" v2="562075888" v3="1088955204" v4="3490709648" v5="329853442" v6="1558891" v7="1316049774" v8="8256" v9="273690640" v10="1362117664" v11="62923065" v12="1972777" v13="23920793" v14="289407689" v15="29">
                    <CSFeature sxBase="2" syBase="7" wBase="2" hBase="4" />
                </CSWeak>
                <CSWeak weigth="0.644599" v0="536872960" v1="167774336" v2="134279760" v3="2432735424" v4="42469504" v5="2361344" v6="2382607344" v7="50855968" v8="134520832" v9="3917484593" v10="268444160" v11="1628459216" v12="2366112256" v13="4216160258" v14="54792464" v15="38277778">
                    <CSFeature sxBase="2" syBase="10" wBase="1" hBase="1" />
                </CSWeak>
                <CSWeak weigth="0.654258" v0="1466990816" v1="67297304" v2="225618664" v3="292593747" v4="1769275490" v5="1201473664" v6="234143802" v7="372650800" v8="1566621928" v9="69206016" v10="307778152" v11="4597998" v12="1411401865" v13="12654760" v14="444664837" v15="6685362">
                    <CSFeature sxBase="3" syBase="3" wBase="2" hBase="5" />
                </CSWeak>
                <CSWeak weigth="0.677864" v0="2151720968" v1="858499184" v2="3154151424" v3="3401744640" v4="8421376" v5="1409321409" v6="1086488832" v7="3496868816" v8="72417" v9="37956387" v10="2147517066" v11="8728" v12="2722" v13="277939059" v14="16788322" v15="318767385">
                    <CSFeature sxBase="7" syBase="14" wBase="1" hBase="2" />
                </CSWeak>
                <CSWeak weigth="0.658276" v0="2438989952" v1="513017864" v2="139461186" v3="20050161" v4="73007288" v5="3312066592" v6="564199472" v7="67199584" v8="1365278922" v9="51718184" v10="180355176" v11="22248398" v12="326249130" v13="22315150" v14="518" v15="5513473">
                    <CSFeature sxBase="4" syBase="6" wBase="2" hBase="4" />
                </CSWeak>
                <CSWeak weigth="0.650722" v0="1044938752" v1="3573893248" v2="3310092288" v3="55972608" v4="422641792" v5="493223936" v6="4202608" v7="458559762" v8="797704896" v9="377946696" v10="965290048" v11="21430816" v12="305217776" v13="270667872" v14="675838349" v15="168167769">
                    <CSFeature sxBase="3" syBase="4" wBase="2" hBase="3" />
                </CSWeak>
                <CSWeak weigth="0.676647" v0="3194976" v1="1262686336" v2="1087408648" v3="7617024" v4="1287323880" v5="299892802" v6="1449888800" v7="3809978" v8="344064200" v9="4194552" v10="2200" v11="1186134" v12="1088882888" v13="46825512" v14="682757280" v15="3605055">
                    <CSFeature sxBase="4" syBase="2" wBase="2" hBase="6" />
                </CSWeak>
                <CSWeak weigth="0.682893" v0="2464153600" v1="847087744" v2="2163224800" v3="52523553" v4="1521565924" v5="1409745120" v6="1218462672" v7="119079668" v8="592445592" v9="806506552" v10="893430408" v11="4259958" v12="1369942061" v13="16267497" v14="6783863" v15="308346889">
                    <CSFeature sxBase="3" syBase="5" wBase="2" hBase="4" />
                </CSWeak>
                <CSWeak weigth="0.668013" v0="8320" v1="531284608" v2="67121344" v3="403931264" v4="3347056640" v5="2248156160" v6="3322454081" v7="131074" v8="2583691392" v9="2071527937" v10="320" v11="1345593344" v12="587203881" v13="1792024984" v14="8409456" v15="100667602">
                    <CSFeature sxBase="2" syBase="11" wBase="1" hBase="2" />
                </CSWeak>
                <CSWeak weigth="0.684675" v0="2025874432" v1="1728380936" v2="69730308" v3="1140269072" v4="3344171008" v5="319291394" v6="351012896" v7="324469265" v8="529009288" v9="336691208" v10="243335364" v11="323223552" v12="1585055752" v13="1141130312" v14="505157852" v15="236482624">
                    <CSFeature sxBase="3" syBase="2" wBase="2" hBase="3" />
                </CSWeak>
                <CSWeak weigth="0.696966" v0="2147516480" v1="37322912" v2="2436913152" v3="63548002" v4="134217856" v5="272629768" v6="134226618" v7="16913236" v8="4237472" v9="21071977" v10="2704" v11="50468088" v12="5867563" v13="52037690" v14="1114242" v15="16908800">
                    <CSFeature sxBase="7" syBase="7" wBase="1" hBase="4" />
                </CSWeak>
                <CSWeak weigth="0.706192" v0="514351168" v1="1025507416" v2="546316352" v3="110920321" v4="2521123008" v5="376047618" v6="2695943265" v7="23680204" v8="889196608" v9="286392448" v10="1429568" v11="302109098" v12="283377742" v13="335551304" v14="86463886" v15="285671562">
                    <CSFeature sxBase="2" syBase="7" wBase="2" hBase="3" />
                </CSWeak>
                <CSWeak weigth="0.680551" v0="34816" v1="2870290528" v2="3758104576" v3="2469433856" v4="1073741824" v5="217391106" v6="2764050560" v7="3221291040" v8="165888" v9="1181067904" v10="2298530816" v11="134408704" v12="3344618" v13="19172176" v14="285614512" v15="38801922">
                    <CSFeature sxBase="3" syBase="14" wBase="2" hBase="2" />
                </CSWeak>
                <CSWeak weigth="0.667520" v0="1215578144" v1="201327056" v2="315671114" v3="673202240" v4="2418212936" v5="3119104" v6="2138492986" v7="67635376" v8="5277696" v9="277348738" v10="279183544" v11="273025566" v12="540413285" v13="22873593" v14="279712456" v15="24201435">
                    <CSFeature sxBase="3" syBase="4" wBase="2" hBase="6" />
                </CSWeak>
                <CSWeak weigth="0.660938" v0="2147526688" v1="569190562" v2="1275070464" v3="2315958282" v4="4202496" v5="2531141684" v6="343932976" v7="20578400" v8="2281709800" v9="56623282" v10="41504" v11="37749312" v12="80742578" v13="65896616" v14="11543338" v15="50397184">
                    <CSFeature sxBase="4" syBase="11" wBase="2" hBase="3" />
                </CSWeak>
                <CSWeak weigth="0.677457" v0="3431464960" v1="2374763648" v2="407378048" v3="970739920" v4="89391104" v5="2219114736" v6="88199216" v7="174063712" v8="8398848" v9="704907810" v10="990650948" v11="943792705" v12="11602059" v13="354427946" v14="276324286" v15="16918464">
                    <CSFeature sxBase="2" syBase="6" wBase="2" hBase="2" />
                </CSWeak>
                <CSWeak weigth="0.669473" v0="1090519104" v1="1626491072" v2="2667627217" v3="165911201" v4="2147516544" v5="25165952" v6="2433902931" v7="1538282450" v8="2155919360" v9="2691696826" v10="302000336" v11="288534544" v12="276971720" v13="2152923266" v14="1607733289" v15="278925474">
                    <CSFeature sxBase="2" syBase="6" wBase="1" hBase="5" />
                </CSWeak>
                <CSWeak weigth="0.677368" v0="1082165248" v1="2604214824" v2="2147487936" v3="200077888" v4="3242461360" v5="1089047182" v6="4060475858" v7="90735711" v8="1098948736" v9="1909991592" v10="1360007232" v11="322130083" v12="2785975" v13="50800712" v14="11616308" v15="268435545">
                    <CSFeature sxBase="2" syBase="9" wBase="2" hBase="3" />
                </CSWeak>
                <CSWeak weigth="0.686543" v0="8390656" v1="1418240018" v2="402686464" v3="2421373328" v4="524288" v5="0" v6="1040192403" v7="318771472" v8="2151688954" v9="1345429528" v10="59488" v11="34673475" v12="39102714" v13="1090977890" v14="1960563" v15="105120330">
                    <CSFeature sxBase="7" syBase="7" wBase="1" hBase="2" />
                </CSWeak>
                <CSWeak weigth="0.669238" v0="424691712" v1="845676672" v2="1087391840" v3="324223488" v4="2179301596" v5="368314950" v6="229223777" v7="3946721" v8="1079030432" v9="12754984" v10="352352361" v11="18227826" v12="272607393" v13="338496008" v14="290488321" v15="35652255">
                    <CSFeature sxBase="3" syBase="6" wBase="2" hBase="4" />
                </CSWeak>
                <CSWeak weigth="0.658925" v0="128" v1="3757318304" v2="50332288" v3="2554360384" v4="2151719144" v5="32800" v6="2424308480" v7="1413481152" v8="8192" v9="1749299872" v10="2382400000" v11="1229146752" v12="67764224" v13="55902836" v14="184814329" v15="525340994">
                    <CSFeature sxBase="2" syBase="15" wBase="2" hBase="1" />
                </CSWeak>
            </CSClassificator>
            <CSClassificator threshold="9.595213">
                <CSWeak weigth="1.043099" v0="61874912" v1="401941010" v2="2434828816" v3="389495083" v4="1441857760" v5="1400242176" v6="1370753080" v7="343346503" v8="385907272" v9="354552440" v10="340796074" v11="104290414" v12="292723248" v13="389481001" v14="118235364" v15="23396611">
                    <CSFeature sxBase="4" syBase="3" wBase="2" hBase="4" />
                </CSWeak>
                <CSWeak weigth="0.938561" v0="3371302944" v1="5800160" v2="3861411912" v3="3116917218" v4="2038136952" v5="58132731" v6="3195065209" v7="99357162" v8="3489689792" v9="4231248" v10="1146147880" v11="13919064" v12="26711074" v13="24545443" v14="3206304103" v15="285213095">
                    <CSFeature sxBase="2" syBase="4" wBase="2" hBase="6" />
                </CSWeak>
                <CSWeak weigth="0.962676" v0="1482737896" v1="1993353832" v2="605610618" v3="57088234" v4="3602776170" v5="1375668458" v6="94370170" v7="275383037" v8="3489663176" v9="31695610" v10="283118154" v11="7474174" v12="301541992" v13="16059071" v14="290654400" v15="1131094847">
                    <CSFeature sxBase="4" syBase="4" wBase="2" hBase="5" />
                </CSWeak>
                <CSWeak weigth="0.927865" v0="3618685152" v1="3936092258" v2="3663257792" v3="1886438112" v4="1375453370" v5="2446141658" v6="2537243031" v7="1249016687" v8="4028649696" v9="270860472" v10="841023696" v11="290503091" v12="2430024339" v13="275126519" v14="1097941293" v15="18219189">
                    <CSFeature sxBase="2" syBase="6" wBase="2" hBase="4" />
                </CSWeak>
                <CSWeak weigth="0.939039" v0="283132096" v1="4100661992" v2="282340068" v3="313788656" v4="3634571356" v5="84347450" v6="4239772017" v7="376131704" v8="1900050960" v9="283714232" v10="269502648" v11="51452512" v12="285190315" v13="10299946" v14="276156991" v15="18883177">
                    <CSFeature sxBase="3" syBase="7" wBase="2" hBase="4" />
                </CSWeak>
                <CSWeak weigth="1.004883" v0="2214084856" v1="81189084" v2="1598056490" v3="728169336" v4="2670264442" v5="1439007600" v6="4293946360" v7="738089455" v8="29360" v9="2417628369" v10="1531976240" v11="7753779" v12="282172313" v13="41257464" v14="4657480" v15="285606208">
                    <CSFeature sxBase="2" syBase="6" wBase="2" hBase="5" />
                </CSWeak>
                <CSWeak weigth="0.975349" v0="3120844800" v1="267700744" v2="3218921664" v3="388313232" v4="1608057024" v5="2436169792" v6="4266969152" v7="1157627977" v8="398752712" v9="2469402416" v10="143348362" v11="324362240" v12="251997178" v13="357966160" v14="481193628" v15="102310245">
                    <CSFeature sxBase="2" syBase="4" wBase="2" hBase="3" />
                </CSWeak>
                <CSWeak weigth="0.985358" v0="677421664" v1="3208587912" v2="2281736192" v3="442546946" v4="876609728" v5="301795572" v6="1373700272" v7="90178418" v8="10486464" v9="303049264" v10="21031600" v11="55648817" v12="22512495" v13="133630591" v14="1165218669" v15="34734285">
                    <CSFeature sxBase="4" syBase="8" wBase="2" hBase="3" />
                </CSWeak>
                <CSWeak weigth="0.942614" v0="1723891784" v1="1246249536" v2="3738733120" v3="2579556480" v4="3595223232" v5="1230258240" v6="1862857409" v7="778244249" v8="4060115328" v9="16263730" v10="3372257376" v11="285213448" v12="3410123200" v13="1363415520" v14="1208077391" v15="290652482">
                    <CSFeature sxBase="3" syBase="3" wBase="1" hBase="5" />
                </CSWeak>
                <CSWeak weigth="0.954631" v0="317819104" v1="1206231784" v2="407960080" v3="393357946" v4="3571187896" v5="1371283514" v6="2018852977" v7="386990897" v8="321913578" v9="318769338" v10="269628390" v11="342840255" v12="435235583" v13="291899447" v14="286460288" v15="274141487">
                    <CSFeature sxBase="4" syBase="5" wBase="2" hBase="4" />
                </CSWeak>
                <CSWeak weigth="0.931735" v0="4175974632" v1="851091696" v2="3447220232" v3="11067872" v4="501942376" v5="37552304" v6="1996028755" v7="32379306" v8="562074728" v9="20975840" v10="1443910176" v11="20992976" v12="1418836216" v13="14094584" v14="2014239707" v15="20202991">
                    <CSFeature sxBase="2" syBase="2" wBase="2" hBase="6" />
                </CSWeak>
                <CSWeak weigth="0.921188" v0="874553408" v1="3862300776" v2="2155926144" v3="454396451" v4="1421901832" v5="1437739194" v6="164974764" v7="68170273" v8="2315258440" v9="319232185" v10="1626868" v11="38107635" v12="32574079" v13="305464047" v14="345418623" v15="54920047">
                    <CSFeature sxBase="4" syBase="7" wBase="2" hBase="3" />
                </CSWeak>
                <CSWeak weigth="0.952813" v0="4169695936" v1="733347858" v2="1137039560" v3="3688423954" v4="2619345096" v5="4249519616" v6="121698440" v7="52236808" v8="2315783368" v9="3515491001" v10="268974332" v11="457519172" v12="279455979" v13="1422525759" v14="169254582" v15="524489993">
                    <CSFeature sxBase="4" syBase="3" wBase="2" hBase="1" />
                </CSWeak>
                <CSWeak weigth="0.958528" v0="2194186368" v1="2504270048" v2="193200832" v3="2989884128" v4="222568672" v5="3484485160" v6="3343184048" v7="390357200" v8="2357493896" v9="2249531968" v10="671617028" v11="307433553" v12="225848053" v13="123798217" v14="372876434" v15="373297426">
                    <CSFeature sxBase="3" syBase="7" wBase="2" hBase="2" />
                </CSWeak>
                <CSWeak weigth="0.973891" v0="4159717576" v1="2493876256" v2="3562598432" v3="393527904" v4="1198538784" v5="1143930976" v6="993352026" v7="275857759" v8="2120250240" v9="1377300800" v10="974234456" v11="302307504" v12="3640599416" v13="87519410" v14="190778875" v15="22029715">
                    <CSFeature sxBase="2" syBase="4" wBase="2" hBase="4" />
                </CSWeak>
                <CSWeak weigth="0.977302" v0="790663248" v1="2847221946" v2="3789600888" v3="191914948" v4="1370147056" v5="1194035832" v6="3325448341" v7="1584354283" v8="272658560" v9="1083236368" v10="1091585056" v11="319820248" v12="16232635" v13="22816955" v14="22090429" v15="16912397">
                    <CSFeature sxBase="2" syBase="7" wBase="2" hBase="4" />
                </CSWeak>
                <CSWeak weigth="0.953132" v0="3409461472" v1="929170034" v2="509889272" v3="291131624" v4="3110387754" v5="1573554330" v6="3072313919" v7="350441723" v8="1073803328" v9="292966584" v10="276080882" v11="58138874" v12="1077090441" v13="283917025" v14="1373404000" v15="5577382">
                    <CSFeature sxBase="3" syBase="4" wBase="2" hBase="5" />
                </CSWeak>
                <CSWeak weigth="0.978695" v0="1187004416" v1="2345722240" v2="3296875594" v3="3292592576" v4="126765792" v5="1858939464" v6="369798940" v7="1363412994" v8="3321911360" v9="3819971105" v10="17572856" v11="1162896833" v12="2677277356" v13="2993923632" v14="1313673561" v15="1313298001">
                    <CSFeature sxBase="2" syBase="13" wBase="1" hBase="1" />
                </CSWeak>
                <CSWeak weigth="1.078362" v0="2158010376" v1="4277471930" v2="134228608" v3="188787208" v4="71829568" v5="2356873298" v6="96489568" v7="2228330" v8="3231722048" v9="36870872" v10="2281724672" v11="33559154" v12="15935859" v13="128395472" v14="3187483" v15="51577723">
                    <CSFeature sxBase="4" syBase="10" wBase="2" hBase="3" />
                </CSWeak>
                <CSWeak weigth="0.998229" v0="66175168" v1="2746662944" v2="4091580664" v3="1171452744" v4="3506487346" v5="881655930" v6="1695673769" v7="337903839" v8="4134596992" v9="1363206256" v10="1196734608" v11="287666488" v12="1265392078" v13="23462126" v14="1311621495" v15="272716291">
                    <CSFeature sxBase="2" syBase="5" wBase="2" hBase="4" />
                </CSWeak>
                <CSWeak weigth="0.974994" v0="2160066784" v1="4033929376" v2="3422584960" v3="2684387840" v4="1083711700" v5="1161109744" v6="471094772" v7="84152400" v8="64" v9="1085840208" v10="59392" v11="536882705" v12="58622396" v13="324346449" v14="408394686" v15="659821315">
                    <CSFeature sxBase="4" syBase="10" wBase="2" hBase="1" />
                </CSWeak>
            </CSClassificator>
            <CSClassificator threshold="14.569943">
                <CSWeak weigth="0.967337" v0="1468556288" v1="740099080" v2="823918592" v3="17106944" v4="294649856" v5="356777984" v6="278953984" v7="33817248" v8="1057518464" v9="4096" v10="395149452" v11="4456448" v12="184560130" v13="13088" v14="1523329774" v15="908208910">
                    <CSFeature sxBase="2" syBase="2" wBase="2" hBase="3" />
                </CSWeak>
                <CSWeak weigth="0.837100" v0="2290089984" v1="4290772992" v2="13111744" v3="557842640" v4="3464560640" v5="2407858176" v6="8413188" v7="205914112" v8="2559051912" v9="16777216" v10="147587272" v11="289407040" v12="109052288" v13="486540288" v14="13145324" v15="521012588">
                    <CSFeature sxBase="3" syBase="3" wBase="2" hBase="2" />
                </CSWeak>
                <CSWeak weigth="0.792152" v0="536879104" v1="52434944" v2="2215177888" v3="3839115304" v4="41984544" v5="3338669200" v6="2417921936" v7="1145438608" v8="83944448" v9="3743469312" v10="214439366" v11="1103118337" v12="1975672234" v13="1559380202" v14="1192514944" v15="1156990178">
                    <CSFeature sxBase="2" syBase="14" wBase="1" hBase="2" />
                </CSWeak>
                <CSWeak weigth="0.719764" v0="1607483392" v1="85401600" v2="201336840" v3="124194947" v4="1349910664" v5="1437728768" v6="2494587392" v7="105259601" v8="218145378" v9="101910586" v10="18139208" v11="125242626" v12="7383798" v13="86386784" v14="54326372" v15="302256420">
                    <CSFeature sxBase="4" syBase="5" wBase="2" hBase="3" />
                </CSWeak>
                <CSWeak weigth="0.714243" v0="268435456" v1="2231369728" v2="3766779912" v3="4023615488" v4="2174813089" v5="3684565426" v6="2160628736" v7="3754039696" v8="144280257" v9="4043370666" v10="475380161" v11="3209798404" v12="562463215" v13="2199913185" v14="353406364" v15="269288070">
                    <CSFeature sxBase="3" syBase="19" wBase="2" hBase="1" />
                </CSWeak>
                <CSWeak weigth="0.675736" v0="2827485184" v1="4105568256" v2="541855808" v3="977309696" v4="2358837440" v5="10748144" v6="2550141040" v7="201642177" v8="2852915208" v9="3741661193" v10="1040197888" v11="302117201" v12="309527266" v13="1409418786" v14="425334012" v15="352338050">
                    <CSFeature sxBase="2" syBase="7" wBase="2" hBase="2" />
                </CSWeak>
                <CSWeak weigth="0.678810" v0="3232235520" v1="283216784" v2="7654040" v3="1441353860" v4="3224666665" v5="1116485800" v6="3165837481" v7="120082728" v8="9470632" v9="2900506" v10="22334640" v11="4534867" v12="28027052" v13="14002920" v14="21397632" v15="131074">
                    <CSFeature sxBase="3" syBase="6" wBase="2" hBase="5" />
                </CSWeak>
                <CSWeak weigth="0.667057" v0="1895843904" v1="1261096960" v2="838922280" v3="297320873" v4="67108864" v5="33554432" v6="3009018050" v7="33555408" v8="453016128" v9="2447458450" v10="453040576" v11="277889160" v12="34363472" v13="262544" v14="168076332" v15="105906195">
                    <CSFeature sxBase="2" syBase="6" wBase="1" hBase="3" />
                </CSWeak>
                <CSWeak weigth="0.650030" v0="8192" v1="4294380064" v2="3355476096" v3="3392199168" v4="5243072" v5="216541920" v6="2153267408" v7="6291552" v8="34920" v9="1092651010" v10="2281750752" v11="16779776" v12="15796934" v13="85992160" v14="92565742" v15="85328384">
                    <CSFeature sxBase="3" syBase="12" wBase="2" hBase="2" />
                </CSWeak>
                <CSWeak weigth="0.652311" v0="2855321792" v1="183913104" v2="1144664808" v3="3817702" v4="2222801128" v5="271550682" v6="804585594" v7="1075839416" v8="809554008" v9="4751424" v10="1348626480" v11="16910567" v12="280722" v13="13370618" v14="3157515208" v15="2754581">
                    <CSFeature sxBase="3" syBase="2" wBase="2" hBase="6" />
                </CSWeak>
                <CSWeak weigth="0.659585" v0="8390720" v1="997659168" v2="4208640" v3="2600503936" v4="8384" v5="163588834" v6="192938208" v7="20979776" v8="134232096" v9="57749568" v10="2285957824" v11="33765376" v12="1322216" v13="16853536" v14="3193526" v15="50399073">
                    <CSFeature sxBase="4" syBase="10" wBase="2" hBase="2" />
                </CSWeak>
                <CSWeak weigth="0.660635" v0="324108448" v1="385493738" v2="407913088" v3="107086360" v4="3564896264" v5="1440229528" v6="1749041232" v7="33891184" v8="319849090" v9="2105960" v10="1223020" v11="88042233" v12="409012478" v13="274082429" v14="6548388" v15="272635239">
                    <CSFeature sxBase="4" syBase="5" wBase="2" hBase="4" />
                </CSWeak>
                <CSWeak weigth="0.660154" v0="150994944" v1="3042415616" v2="134480000" v3="402068466" v4="289669120" v5="359792640" v6="1346926600" v7="34867187" v8="2911641664" v9="120782896" v10="164147912" v11="74908210" v12="135876169" v13="337645610" v14="1164728412" v15="50611048">
                    <CSFeature sxBase="4" syBase="3" wBase="2" hBase="3" />
                </CSWeak>
                <CSWeak weigth="0.676257" v0="128" v1="3263170624" v2="1099005954" v3="2990899200" v4="9210272" v5="2702905537" v6="2157023565" v7="3844346373" v8="3229909120" v9="2868945536" v10="2299308107" v11="2382734981" v12="2172981569" v13="2158764707" v14="184951117" v15="5636370">
                    <CSFeature sxBase="2" syBase="18" wBase="2" hBase="1" />
                </CSWeak>
                <CSWeak weigth="0.701186" v0="2455764992" v1="3760335392" v2="2483027968" v3="516426338" v4="336068608" v5="208079494" v6="2486485060" v7="224805068" v8="3248545922" v9="3764553730" v10="2101632" v11="1400045866" v12="29665491" v13="1145610436" v14="351551570" v15="131112">
                    <CSFeature sxBase="2" syBase="10" wBase="2" hBase="3" />
                </CSWeak>
                <CSWeak weigth="0.667794" v0="417865928" v1="3503867916" v2="1615364104" v3="310903243" v4="3504931048" v5="3632603312" v6="2187953164" v7="625561616" v8="243278024" v9="3226208256" v10="29907140" v11="1380057180" v12="88674966" v13="855638466" v14="323114351" v15="318908235">
                    <CSFeature sxBase="3" syBase="3" wBase="2" hBase="1" />
                </CSWeak>
                <CSWeak weigth="0.700087" v0="2970673248" v1="103319552" v2="3504404512" v3="576086098" v4="324862148" v5="270600360" v6="2517516899" v7="101646582" v8="1937805464" v9="1052848" v10="808741496" v11="273817716" v12="1345423397" v13="288765963" v14="8818688" v15="34996792">
                    <CSFeature sxBase="3" syBase="5" wBase="2" hBase="4" />
                </CSWeak>
                <CSWeak weigth="0.658300" v0="862978184" v1="1411391648" v2="268470512" v3="53478056" v4="1366294760" v5="1095368746" v6="624566954" v7="4662851" v8="1431355552" v9="14688440" v10="8388798" v11="3607551" v12="37096045" v13="301471930" v14="272835577" v15="23277899">
                    <CSFeature sxBase="4" syBase="2" wBase="2" hBase="5" />
                </CSWeak>
                <CSWeak weigth="0.640129" v0="2338898048" v1="18366544" v2="1262528648" v3="54584272" v4="762118176" v5="149817498" v6="582900487" v7="101216956" v8="2424590896" v9="273727565" v10="1433462928" v11="22086533" v12="1084592803" v13="293194456" v14="475138280" v15="5374431">
                    <CSFeature sxBase="2" syBase="5" wBase="2" hBase="5" />
                </CSWeak>
                <CSWeak weigth="0.650598" v0="134227968" v1="3572770976" v2="218366976" v3="2814558209" v4="2349072592" v5="1261210184" v6="428916976" v7="67129568" v8="2290094080" v9="1371744768" v10="134262912" v11="302067717" v12="149981921" v13="100675136" v14="1462797050" v15="353763362">
                    <CSFeature sxBase="3" syBase="8" wBase="2" hBase="2" />
                </CSWeak>
                <CSWeak weigth="0.648208" v0="3758097408" v1="2937094656" v2="2521409568" v3="3461927082" v4="2147484800" v5="3322413072" v6="345294609" v7="348127488" v8="1358987648" v9="3530644777" v10="525458" v11="1448231325" v12="1166597322" v13="3572735404" v14="1099568616" v15="1415059374">
                    <CSFeature sxBase="2" syBase="15" wBase="1" hBase="2" />
                </CSWeak>
                <CSWeak weigth="0.659937" v0="580911104" v1="3241814600" v2="268470272" v3="1796268128" v4="67143680" v5="3427207362" v6="4194377" v7="520703079" v8="565209280" v9="1365263874" v10="2231404560" v11="2460160960" v12="12296296" v13="1430365313" v14="282112424" v15="71499905">
                    <CSFeature sxBase="2" syBase="12" wBase="2" hBase="3" />
                </CSWeak>
                <CSWeak weigth="0.674543" v0="1216348160" v1="2716510336" v2="2281720320" v3="713079456" v4="76816448" v5="27601106" v6="255877120" v7="73400896" v8="48674" v9="6291968" v10="138731652" v11="51448144" v12="2369780" v13="1125589874" v14="290647714" v15="50334211">
                    <CSFeature sxBase="4" syBase="9" wBase="2" hBase="2" />
                </CSWeak>
                <CSWeak weigth="0.661603" v0="1934671880" v1="515033632" v2="1122009112" v3="87164962" v4="1438187760" v5="70713536" v6="2384613684" v7="1343684779" v8="4078715080" v9="272785416" v10="1898748818" v11="2505347232" v12="357826572" v13="106304284" v14="1882012713" v15="152319289">
                    <CSFeature sxBase="2" syBase="3" wBase="2" hBase="4" />
                </CSWeak>
                <CSWeak weigth="0.671063" v0="810590240" v1="2024611842" v2="4216928" v3="1229177537" v4="1104676872" v5="218180290" v6="3586150816" v7="1769826" v8="310411792" v9="274047152" v10="16834624" v11="554790963" v12="7383157" v13="6293716" v14="70666867" v15="2219">
                    <CSFeature sxBase="3" syBase="8" wBase="2" hBase="3" />
                </CSWeak>
                <CSWeak weigth="0.679440" v0="2147493952" v1="3207563944" v2="3355445824" v3="169484840" v4="5275680" v5="2311072416" v6="494932096" v7="64" v8="10400" v9="100772384" v10="2285955200" v11="8704" v12="30550265" v13="70623266" v14="87439584" v15="16973858">
                    <CSFeature sxBase="4" syBase="12" wBase="2" hBase="2" />
                </CSWeak>
                <CSWeak weigth="0.668477" v0="2820669600" v1="537026704" v2="3700959464" v3="2130304" v4="161155176" v5="60096688" v6="515170858" v7="11141410" v8="3716174952" v9="4214928" v10="1313102352" v11="17842528" v12="67479680" v13="12931074" v14="555935818" v15="22369295">
                    <CSFeature sxBase="2" syBase="2" wBase="2" hBase="6" />
                </CSWeak>
                <CSWeak weigth="0.657774" v0="4269801472" v1="2567446528" v2="302776384" v3="676594176" v4="201654272" v5="1287651328" v6="436801600" v7="373555216" v8="2903255616" v9="58723840" v10="180887744" v11="37761536" v12="9439432" v13="83927072" v14="139730638" v15="1966221955">
                    <CSFeature sxBase="2" syBase="4" wBase="2" hBase="2" />
                </CSWeak>
                <CSWeak weigth="0.654853" v0="2688581664" v1="78234274" v2="2147787016" v3="2165850408" v4="3650289754" v5="101079688" v6="740182333" v7="39326178" v8="2340422178" v9="139069704" v10="285214898" v11="397875" v12="286182292" v13="32440742" v14="6560188" v15="1378560">
                    <CSFeature sxBase="3" syBase="7" wBase="2" hBase="5" />
                </CSWeak>
                <CSWeak weigth="0.653243" v0="291520544" v1="1117802552" v2="3000029368" v3="458440800" v4="2025342985" v5="446073952" v6="2474398007" v7="69816741" v8="1342226658" v9="311198400" v10="1347856538" v11="3551460" v12="1074411522" v13="277850311" v14="1078824692" v15="197450">
                    <CSFeature sxBase="3" syBase="5" wBase="2" hBase="5" />
                </CSWeak>
                <CSWeak weigth="0.633239" v0="9224192" v1="469844096" v2="8913096" v3="289870544" v4="3300917248" v5="218300416" v6="1145045200" v7="16779635" v8="201903240" v9="352518432" v10="88899596" v11="64430656" v12="134234122" v13="354557968" v14="1271665101" v15="626275390">
                    <CSFeature sxBase="4" syBase="2" wBase="2" hBase="3" />
                </CSWeak>
                <CSWeak weigth="0.663372" v0="378056704" v1="3154509832" v2="209750144" v3="982975395" v4="290455680" v5="487981056" v6="811074084" v7="1410542401" v8="218382340" v9="353847312" v10="227289088" v11="57999938" v12="1349542096" v13="287519304" v14="91027756" v15="39849994">
                    <CSFeature sxBase="4" syBase="4" wBase="2" hBase="3" />
                </CSWeak>
                <CSWeak weigth="0.642222" v0="150996992" v1="4244643840" v2="453005536" v3="4219486608" v4="0" v5="184549376" v6="813773040" v7="453247104" v8="436757392" v9="2063119056" v10="34110024" v11="33575360" v12="33560835" v13="16777905" v14="33872382" v15="1140986509">
                    <CSFeature sxBase="2" syBase="6" wBase="1" hBase="2" />
                </CSWeak>
                <CSWeak weigth="0.658267" v0="612897259" v1="998008858" v2="29928" v3="2572734552" v4="1174437952" v5="2563899392" v6="1347974227" v7="186388489" v8="277358793" v9="3507094959" v10="134756480" v11="236528194" v12="571745768" v13="663422592" v14="453507900" v15="101847658">
                    <CSFeature sxBase="7" syBase="2" wBase="1" hBase="1" />
                </CSWeak>
                <CSWeak weigth="0.654827" v0="3530047616" v1="645989018" v2="1516266008" v3="25116794" v4="1232486442" v5="430704778" v6="3009661067" v7="27349185" v8="6320328" v9="24527024" v10="1349834858" v11="51511511" v12="1082173633" v13="283917026" v14="25387772" v15="24385706">
                    <CSFeature sxBase="3" syBase="4" wBase="2" hBase="5" />
                </CSWeak>
                <CSWeak weigth="0.642834" v0="437289152" v1="1011638304" v2="2219065504" v3="861340483" v4="325058696" v5="1565788856" v6="370442440" v7="258736196" v8="756023360" v9="285217361" v10="1057091680" v11="289738804" v12="1147896375" v13="19081798" v14="1368174053" v15="39059768">
                    <CSFeature sxBase="3" syBase="6" wBase="2" hBase="3" />
                </CSWeak>
                <CSWeak weigth="0.630406" v0="1231030408" v1="2167590992" v2="218136800" v3="2799755552" v4="2523865194" v5="29048880" v6="3461351936" v7="69882236" v8="1074849992" v9="269500769" v10="3678503590" v11="287458209" v12="1345112163" v13="30740696" v14="2595384528" v15="50544795">
                    <CSFeature sxBase="2" syBase="4" wBase="2" hBase="5" />
                </CSWeak>
                <CSWeak weigth="0.655965" v0="3119513672" v1="2254555296" v2="3042492576" v3="67174944" v4="28311552" v5="1078919200" v6="1392531864" v7="352387535" v8="2019586880" v9="1377079728" v10="1882308984" v11="33839136" v12="3635360296" v13="354824368" v14="453971117" v15="272770516">
                    <CSFeature sxBase="2" syBase="4" wBase="2" hBase="4" />
                </CSWeak>
                <CSWeak weigth="0.635504" v0="536903688" v1="1651746816" v2="412108800" v3="1504919744" v4="3296722944" v5="1147142280" v6="2651003464" v7="255000738" v8="1363202184" v9="3508883874" v10="83918978" v11="1366425736" v12="92307658" v13="1281235940" v14="2992570535" v15="1356464382">
                    <CSFeature sxBase="3" syBase="13" wBase="1" hBase="3" />
                </CSWeak>
                <CSWeak weigth="0.663417" v0="536871424" v1="3412869248" v2="34078904" v3="2572714664" v4="2659225344" v5="3289528320" v6="34613876" v7="1413808322" v8="587252864" v9="1996533416" v10="1280" v11="1383121393" v12="3394899816" v13="3202645024" v14="1528094416" v15="1145963622">
                    <CSFeature sxBase="2" syBase="12" wBase="1" hBase="2" />
                </CSWeak>
                <CSWeak weigth="0.650080" v0="1119887360" v1="863479848" v2="3363831808" v3="2743175688" v4="3145904" v5="3117886114" v6="1157628544" v7="33554496" v8="2283833570" v9="19990544" v10="2147527328" v11="50422274" v12="12069106" v13="70429184" v14="18124929" v15="33816584">
                    <CSFeature sxBase="4" syBase="13" wBase="2" hBase="2" />
                </CSWeak>
                <CSWeak weigth="0.678469" v0="4124049504" v1="2477293762" v2="3523780768" v3="826393280" v4="2503803122" v5="3025018" v6="3448965487" v7="1478763463" v8="2973777920" v9="272900136" v10="841040048" v11="269789587" v12="2431662768" v13="272898291" v14="2179212" v15="1442023">
                    <CSFeature sxBase="2" syBase="6" wBase="2" hBase="4" />
                </CSWeak>
                <CSWeak weigth="0.654306" v0="2785552522" v1="3313771016" v2="1790989508" v3="2436931600" v4="3921674248" v5="2348810304" v6="2149109952" v7="1291878912" v8="2160624256" v9="3347876234" v10="69748292" v11="907018376" v12="71696394" v13="1451761704" v14="6019564" v15="2000189383">
                    <CSFeature sxBase="2" syBase="4" wBase="2" hBase="1" />
                </CSWeak>
                <CSWeak weigth="0.681248" v0="2148532224" v1="172228608" v2="8421440" v3="1358811664" v4="41943176" v5="3447062528" v6="4722936" v7="1750089808" v8="2290624512" v9="2870805569" v10="8913096" v11="322970320" v12="281020489" v13="720912" v14="1431065182" v15="1346909254">
                    <CSFeature sxBase="4" syBase="2" wBase="2" hBase="2" />
                </CSWeak>
            </CSClassificator>
            <CSClassificator threshold="10.402978">
                <CSWeak weigth="0.974985" v0="1214251080" v1="1960878304" v2="874045682" v3="58101864" v4="3598483562" v5="1345585378" v6="368137080" v7="296362221" v8="3489695840" v9="23210512" v10="283117690" v11="6427630" v12="301410346" v13="275679866" v14="286067056" v15="1114177584">
                    <CSFeature sxBase="4" syBase="4" wBase="2" hBase="5" />
                </CSWeak>
                <CSWeak weigth="0.850400" v0="2686484544" v1="392405552" v2="2432754240" v3="573581521" v4="1082392636" v5="1278714622" v6="3579691381" v7="120932444" v8="546349736" v9="280993912" v10="134240960" v11="50404224" v12="74549356" v13="4991184" v14="1412839551" v15="51380655">
                    <CSFeature sxBase="3" syBase="9" wBase="2" hBase="3" />
                </CSWeak>
                <CSWeak weigth="0.881554" v0="4168188096" v1="116015200" v2="3914354744" v3="1168356328" v4="3710943474" v5="2012020842" v6="1815211261" v7="342048895" v8="4098929024" v9="1077952544" v10="1460725952" v11="23409144" v12="173300094" v13="7475268" v14="1445298443" v15="82514">
                    <CSFeature sxBase="2" syBase="5" wBase="2" hBase="4" />
                </CSWeak>
                <CSWeak weigth="0.825561" v0="3581978752" v1="2032410784" v2="3256909824" v3="1570162768" v4="80781312" v5="212477998" v6="2290665759" v7="260001872" v8="2191556736" v9="1366500025" v10="176220288" v11="870486019" v12="278202371" v13="1197976241" v14="23081682" v15="12910967">
                    <CSFeature sxBase="2" syBase="11" wBase="2" hBase="3" />
                </CSWeak>
                <CSWeak weigth="0.860253" v0="3389040832" v1="3086551200" v2="218408000" v3="3951141393" v4="2334466080" v5="1592560216" v6="1997586737" v7="525684848" v8="2155886624" v9="1372915808" v10="134254720" v11="302068069" v12="164997363" v13="124071699" v14="104014554" v15="16974176">
                    <CSFeature sxBase="3" syBase="8" wBase="2" hBase="2" />
                </CSWeak>
                <CSWeak weigth="0.869224" v0="217632824" v1="2699313392" v2="4262764586" v3="1683649250" v4="2641985656" v5="1353646258" v6="796283051" v7="80417143" v8="4183347696" v9="18890992" v10="2100344848" v11="292582376" v12="1372811512" v13="1331226" v14="446835501" v15="286548423">
                    <CSFeature sxBase="2" syBase="3" wBase="2" hBase="5" />
                </CSWeak>
                <CSWeak weigth="0.870376" v0="4039114888" v1="2234796096" v2="3883462816" v3="376816240" v4="3376168992" v5="23134400" v6="913330610" v7="335626623" v8="1818259968" v9="1377272224" v10="2066854776" v11="302307504" v12="3655283560" v13="338829427" v14="424107891" v15="289809831">
                    <CSFeature sxBase="2" syBase="4" wBase="2" hBase="4" />
                </CSWeak>
                <CSWeak weigth="0.838311" v0="3500179648" v1="1874108648" v2="2286989538" v3="862124563" v4="1148584120" v5="3307022442" v6="1974555264" v7="341860417" v8="1499507298" v9="24519240" v10="182464586" v11="20140536" v12="326468215" v13="276212346" v14="275975082" v15="290792323">
                    <CSFeature sxBase="4" syBase="6" wBase="2" hBase="4" />
                </CSWeak>
                <CSWeak weigth="0.845344" v0="3555248296" v1="3521302672" v2="3473981568" v3="2792526832" v4="67051594" v5="300826872" v6="1595884019" v7="337529342" v8="705739000" v9="287330593" v10="3740398246" v11="291726185" v12="1103091825" v13="280432816" v14="3653396900" v15="57688202">
                    <CSFeature sxBase="2" syBase="4" wBase="2" hBase="5" />
                </CSWeak>
                <CSWeak weigth="0.848514" v0="2583955464" v1="3322413056" v2="2944698376" v3="4241948672" v4="153461665" v5="3486450130" v6="3330651161" v7="3608353153" v8="144279617" v9="4291416744" v10="475371969" v11="3183839765" v12="546276327" v13="2150900674" v14="269848045" v15="319292358">
                    <CSFeature sxBase="3" syBase="19" wBase="2" hBase="1" />
                </CSWeak>
                <CSWeak weigth="0.862484" v0="142641184" v1="192882898" v2="1168114416" v3="57237578" v4="39780488" v5="78318186" v6="1350181080" v7="87099513" v8="2290133608" v9="14715114" v10="1275638754" v11="538834" v12="6357027" v13="15305318" v14="3212082" v15="288490027">
                    <CSFeature sxBase="4" syBase="8" wBase="2" hBase="4" />
                </CSWeak>
                <CSWeak weigth="0.887820" v0="1493222144" v1="126390466" v2="1040236928" v3="1476428232" v4="1174405248" v5="16777216" v6="3725652176" v7="16846976" v8="4076925760" v9="2014343744" v10="402680008" v11="268451968" v12="452994042" v13="12587857" v14="269393599" v15="1411449111">
                    <CSFeature sxBase="2" syBase="4" wBase="1" hBase="3" />
                </CSWeak>
                <CSWeak weigth="0.926016" v0="3673473248" v1="843645000" v2="1615915096" v3="1088481480" v4="429295738" v5="284625120" v6="3174388096" v7="19873896" v8="4770008" v9="277250234" v10="275837178" v11="273033622" v12="7331306" v13="31885898" v14="1347717030" v15="278272993">
                    <CSFeature sxBase="3" syBase="3" wBase="2" hBase="6" />
                </CSWeak>
                <CSWeak weigth="0.874596" v0="1389373640" v1="1382400224" v2="1423196896" v3="929366246" v4="4259922016" v5="1546846210" v6="2604155562" v7="375590978" v8="2135949504" v9="3529703608" v10="525672481" v11="393682994" v12="192389174" v13="1179763" v14="1244076868" v15="337326967">
                    <CSFeature sxBase="3" syBase="3" wBase="2" hBase="4" />
                </CSWeak>
                <CSWeak weigth="0.877134" v0="3007348808" v1="2128756872" v2="4051755072" v3="533821643" v4="2315288576" v5="0" v6="3611335641" v7="385962194" v8="4177580224" v9="869322928" v10="4211088328" v11="268439552" v12="1493215824" v13="297816064" v14="139270197" v15="12911178">
                    <CSFeature sxBase="2" syBase="4" wBase="1" hBase="4" />
                </CSWeak>
                <CSWeak weigth="0.877422" v0="4085309664" v1="1733134400" v2="3583152640" v3="594703057" v4="1599946860" v5="1157826600" v6="1400591285" v7="73269877" v8="1926297720" v9="894652664" v10="896846504" v11="7405680" v12="1343400060" v13="284825747" v14="1439138668" v15="323027739">
                    <CSFeature sxBase="3" syBase="5" wBase="2" hBase="4" />
                </CSWeak>
                <CSWeak weigth="0.891840" v0="918585856" v1="2509276352" v2="2319485568" v3="798781520" v4="2660565184" v5="2303000816" v6="453886064" v7="526651616" v8="2290132992" v9="4202801186" v10="725629124" v11="994128449" v12="150800570" v13="275195410" v14="494682926" v15="286402402">
                    <CSFeature sxBase="2" syBase="6" wBase="2" hBase="2" />
                </CSWeak>
                <CSWeak weigth="0.893265" v0="4011905232" v1="172173514" v2="3772836088" v3="1534591868" v4="3309224176" v5="1174342266" v6="2665042091" v7="1547059637" v8="1346400256" v9="1100001488" v10="1093686368" v11="331362713" v12="10726097" v13="3016955" v14="19989165" v15="1183821">
                    <CSFeature sxBase="2" syBase="7" wBase="2" hBase="4" />
                </CSWeak>
                <CSWeak weigth="0.934370" v0="134219776" v1="1979304480" v2="2457895552" v3="4044391104" v4="2147483648" v5="475209888" v6="2281701505" v7="4044357761" v8="536871040" v9="2155195322" v10="2164279688" v11="184673042" v12="3571842" v13="2239072809" v14="379687626" v15="102039555">
                    <CSFeature sxBase="3" syBase="15" wBase="2" hBase="2" />
                </CSWeak>
                <CSWeak weigth="0.910843" v0="2202534016" v1="122994824" v2="492097600" v3="1566654472" v4="720634016" v5="188940512" v6="2964439185" v7="160710905" v8="3875551304" v9="2470453410" v10="244644424" v11="319869089" v12="1337211834" v13="275196694" v14="1599897064" v15="489126995">
                    <CSFeature sxBase="2" syBase="5" wBase="2" hBase="3" />
                </CSWeak>
                <CSWeak weigth="0.884196" v0="3231760608" v1="1174350376" v2="282354372" v3="398928528" v4="3709733020" v5="1275830392" v6="3983395317" v7="33116282" v8="1896929968" v9="282796584" v10="1065144" v11="16845410" v12="12558889" v13="301933298" v14="272879789" v15="19145241">
                    <CSFeature sxBase="3" syBase="7" wBase="2" hBase="4" />
                </CSWeak>
                <CSWeak weigth="0.888850" v0="3221258248" v1="1901169336" v2="1107350024" v3="2203169584" v4="144441856" v5="4194304" v6="268449547" v7="51380512" v8="134261466" v9="50170584" v10="33619864" v11="16988531" v12="1079419610" v13="376768611" v14="1351916" v15="4522521">
                    <CSFeature sxBase="7" syBase="8" wBase="1" hBase="2" />
                </CSWeak>
                <CSWeak weigth="0.922942" v0="4085285024" v1="1037447650" v2="2455765728" v3="997227152" v4="350715904" v5="1077127400" v6="2532858145" v7="1446140279" v8="3783278720" v9="3511003640" v10="16576" v11="24318081" v12="1551059" v13="72788660" v14="283246634" v15="18088315">
                    <CSFeature sxBase="2" syBase="9" wBase="2" hBase="4" />
                </CSWeak>
                <CSWeak weigth="0.923014" v0="66128096" v1="1206692074" v2="410053232" v3="105319034" v4="3573285080" v5="1425680570" v6="963988033" v7="393683761" v8="36735714" v9="324078296" v10="269638126" v11="359479981" v12="424880174" v13="20980314" v14="269802273" v15="288622417">
                    <CSFeature sxBase="4" syBase="5" wBase="2" hBase="4" />
                </CSWeak>
                <CSWeak weigth="0.905277" v0="3648047168" v1="4100825312" v2="1097936" v3="607412736" v4="3514572828" v5="1293879341" v6="3427952029" v7="86669941" v8="1079030384" v9="277913704" v10="353423977" v11="269886016" v12="289966773" v13="90344099" v14="295078372" v15="269942943">
                    <CSFeature sxBase="3" syBase="6" wBase="2" hBase="4" />
                </CSWeak>
            </CSClassificator>
        </TSCObjectDetector>
    </ILFObjectDetector>
</TLFDetectEngine>
